boatface/__init__.py
boatface/app.py
boatface/cli.py
boatface/core.py
boatface/model.py
boatface/render.py
boatface/util.py
boatface/assets/__init__.py
boatface/assets/awa.png
boatface/assets/display.otf
boatface/assets/main.png
boatface/assets/twa.png
boatface-0.0.2.dist-info/LICENSE
boatface-0.0.2.dist-info/METADATA
boatface-0.0.2.dist-info/WHEEL
boatface-0.0.2.dist-info/entry_points.txt
boatface-0.0.2.dist-info/top_level.txt
boatface-0.0.2.dist-info/RECORD
