Metadata-Version: 2.1
Name: boatface
Version: 0.0.2
Summary: Instrumentation panel for displaying NMEA and SignalK telemetry data
Home-page: https://github.com/maritime-labs/boatface
Download-URL: https://pypi.org/project/boatface/
Author: Holger Marseille
Author-email: ml@argonauta.studio
Maintainer: Andreas Motl
Maintainer-email: andreas.motl@panodata.org
License: AGPL-3.0, EUPL-1.2
Keywords: instrumentation,navigation,panel,display,opencpn,signalk,openplotter,nmea,nmea-0183,sailing,sensor,environmental-monitoring,e-ink,kindle,kobo,tolino
Classifier: Programming Language :: Python
Classifier: Programming Language :: Python :: 3
Classifier: Programming Language :: Python :: 3.6
Classifier: Programming Language :: Python :: 3.7
Classifier: Programming Language :: Python :: 3.8
Classifier: Programming Language :: Python :: 3.9
Classifier: Programming Language :: Python :: 3.10
Classifier: License :: OSI Approved :: GNU Affero General Public License v3
Classifier: License :: OSI Approved :: European Union Public Licence 1.2 (EUPL 1.2)
Classifier: Development Status :: 3 - Alpha
Classifier: Operating System :: POSIX :: Linux
Classifier: Operating System :: MacOS
Classifier: Natural Language :: English
Classifier: Intended Audience :: Customer Service
Classifier: Intended Audience :: Developers
Classifier: Intended Audience :: Education
Classifier: Intended Audience :: Information Technology
Classifier: Intended Audience :: Manufacturing
Classifier: Intended Audience :: Science/Research
Classifier: Intended Audience :: System Administrators
Classifier: Intended Audience :: Telecommunications Industry
Classifier: Topic :: Communications
Classifier: Topic :: Education :: Testing
Classifier: Topic :: Software Development :: Libraries
Classifier: Topic :: Scientific/Engineering
Classifier: Topic :: System :: Emulators
Classifier: Topic :: System :: Networking
Classifier: Topic :: Utilities
License-File: LICENSE
Requires-Dist: asyncio-dgram (<3,>2)
Requires-Dist: pynmea2 (<2,>1)
Requires-Dist: Pillow (<10)
Requires-Dist: click (<9)
Requires-Dist: dataclasses ; python_version <= "3.6"
Requires-Dist: importlib-metadata ; python_version <= "3.7"
Provides-Extra: test
Requires-Dist: pytest (<8) ; extra == 'test'
Requires-Dist: pytest-cov (<4) ; extra == 'test'
Provides-Extra: ui
Requires-Dist: pyglet (<2) ; extra == 'ui'
Requires-Dist: pysdl2 (<1) ; extra == 'ui'
